{
    "name": "scene",
    "objects": [
        {
            "type": "LIGHT",
            "name": "Light",
            "transform": {
                "translation": [
                    4.076245307922363,
                    1.0054539442062378,
                    5.903861999511719
                ],
                "rotation": [
                    37.26104736328125,
                    3.1637091636657715,
                    106.93632507324219
                ],
                "scaling": [
                    1.0,
                    0.9999999403953552,
                    1.0
                ]
            }
        },
        {
            "type": "CAMERA",
            "name": "Camera",
            "transform": {
                "translation": [
                    7.358891487121582,
                    -6.925790786743164,
                    4.958309173583984
                ],
                "rotation": [
                    63.559295654296875,
                    2.2983238068263745e-07,
                    46.69194412231445
                ],
                "scaling": [
                    1.0,
                    1.0,
                    1.0
                ]
            }
        },
        {
            "type": "MESH",
            "name": "Cube",
            "transform": {
                "translation": [
                    0.0,
                    0.0,
                    0.0
                ],
                "rotation": [
                    0.0,
                    -0.0,
                    35.79999923706055
                ],
                "scaling": [
                    1.0,
                    1.0,
                    1.0
                ]
            },
            "file_name": "cube.obj"
        },
        {
            "type": "MESH",
            "name": "Cube.001",
            "transform": {
                "translation": [
                    4.327661991119385,
                    0.0,
                    0.0
                ],
                "rotation": [
                    47.799991607666016,
                    35.69999694824219,
                    35.19999694824219
                ],
                "scaling": [
                    1.0,
                    1.0,
                    1.0
                ]
            },
            "file_name": "cube.obj"
        },
        {
            "type": "MESH",
            "name": "Cube.002",
            "transform": {
                "translation": [
                    7.561161041259766,
                    0.0,
                    0.0
                ],
                "rotation": [
                    0.0,
                    -0.0,
                    0.0
                ],
                "scaling": [
                    1.0,
                    1.0,
                    1.0
                ]
            },
            "file_name": "cube.obj"
        },
        {
            "type": "MESH",
            "name": "Cube.003",
            "transform": {
                "translation": [
                    -3.364144802093506,
                    0.0,
                    0.0
                ],
                "rotation": [
                    0.0,
                    36.60000228881836,
                    0.0
                ],
                "scaling": [
                    0.9999999403953552,
                    1.0,
                    0.9999999403953552
                ]
            },
            "file_name": "cube.obj"
        },
        {
            "type": "MESH",
            "name": "Cube.004",
            "transform": {
                "translation": [
                    -6.858936309814453,
                    0.0,
                    0.0
                ],
                "rotation": [
                    34.19999694824219,
                    -0.0,
                    0.0
                ],
                "scaling": [
                    1.0,
                    0.9999999403953552,
                    0.9999999403953552
                ]
            },
            "file_name": "cube.obj"
        },
        {
            "type": "MESH",
            "name": "Cube_Cube.001",
            "transform": {
                "translation": [
                    4.679755210876465,
                    0.0,
                    2.8219621181488037
                ],
                "rotation": [
                    33.79999923706055,
                    14.40000057220459,
                    27.100000381469727
                ],
                "scaling": [
                    1.0,
                    1.0,
                    1.0
                ]
            },
            "file_name": "axis.obj"
        }
    ]
}